MANIFEST.in
setup.cfg
setup.py
friendly_fenced_tabs/__init__.py
friendly_fenced_tabs/compiler.py
friendly_fenced_tabs/parser.py
friendly_fenced_tabs/reader.py
friendly_fenced_tabs/tab_recollector.py
friendly_fenced_tabs/template.html
friendly_fenced_tabs.egg-info/PKG-INFO
friendly_fenced_tabs.egg-info/SOURCES.txt
friendly_fenced_tabs.egg-info/dependency_links.txt
friendly_fenced_tabs.egg-info/not-zip-safe
friendly_fenced_tabs.egg-info/requires.txt
friendly_fenced_tabs.egg-info/top_level.txt
friendly_fenced_tabs/utils/__init__.py