Metadata-Version: 1.1
Name: friendly-fenced-tabs
Version: 0.0.9
Summary: Generates a html estructure for handling tabbed content
Home-page: https://github.com/andru255/friendly_fenced_tabs
Author: Andres Munoz
Author-email: andru255@gmail.com
License: MIT
Keywords: fenced code blocks,code,fenced,tabs,mkdocs,markdown
Platform: UNKNOWN
Classifier: License :: OSI Approved :: MIT License
Classifier: Operating System :: OS Independent
Classifier: Programming Language :: Python
Classifier: Programming Language :: Python :: 2
Classifier: Topic :: Software Development :: Libraries :: Python Modules
